cereal_lazer/__init__.py
cereal_lazer/cereal.py
cereal_lazer/naive_serializing.py
cereal_lazer-0.1.6.dist-info/AUTHORS
cereal_lazer-0.1.6.dist-info/LICENSE
cereal_lazer-0.1.6.dist-info/METADATA
cereal_lazer-0.1.6.dist-info/WHEEL
cereal_lazer-0.1.6.dist-info/pbr.json
cereal_lazer-0.1.6.dist-info/top_level.txt
cereal_lazer-0.1.6.dist-info/RECORD
