Metadata-Version: 2.1
Name: cereal-lazer
Version: 0.1.6
Summary: Small layer on top of Serialize package that allows to register objects by name instead of namespace
Home-page: https://github.com/maarten-dp/cereal-lazer
Author: Maarten De Paepe
Author-email: "maarten.de.paepe@gmail.com"
License: UNKNOWN
Platform: UNKNOWN
Classifier: Development Status :: 4 - Beta
Classifier: Operating System :: MacOS :: MacOS X
Classifier: Operating System :: Microsoft :: Windows
Classifier: Operating System :: POSIX
Classifier: License :: OSI Approved :: MIT License
Classifier: Programming Language :: Python
Classifier: Programming Language :: Python :: 3.6
Requires-Dist: msgpack (==0.6.1)
Requires-Dist: pbr (>=3.0)
Requires-Dist: pytz
